{"cameraMode":{"drawMode":0,"name":"Shaded","section":"Shading Mode"},"sceneLighting":true,"audioPlay":false,"sceneViewState":{"showFog":true,"showMaterialUpdate":false,"showSkybox":true,"showFlares":true,"showImageEffects":true,"showParticleSystems":true},"in2DMode":false,"pivot":{"x":-3.694861650466919,"y":1.3329377174377442,"z":7.645565986633301},"rotation":{"x":0.15150731801986695,"y":0.5808011889457703,"z":-0.11111120134592056,"w":0.7921102643013},"size":2.235720634460449,"orthographic":false}